etrap_sdk/__init__.py
etrap_sdk/client.py
etrap_sdk/exceptions.py
etrap_sdk/models.py
etrap_sdk/py.typed
etrap_sdk/utils.py
etrap_sdk-0.1.0.dist-info/METADATA
etrap_sdk-0.1.0.dist-info/WHEEL
etrap_sdk-0.1.0.dist-info/licenses/LICENSE
etrap_sdk-0.1.0.dist-info/RECORD
