Metadata-Version: 2.4
Name: etrap-sdk
Version: 0.1.0
Summary: Python SDK for ETRAP - Enterprise Transaction Recording and Audit Platform
Author-email: Marco Graziano <marco@graziano.com>
License-File: LICENSE
Requires-Python: >=3.8
Requires-Dist: boto3>=1.26.0
Requires-Dist: py-near==1.1.52
Requires-Dist: pydantic>=2.0.0
Requires-Dist: python-dateutil>=2.8.0
Requires-Dist: typing-extensions>=4.5.0
Provides-Extra: dev
Requires-Dist: black>=23.0.0; extra == 'dev'
Requires-Dist: mypy>=1.0.0; extra == 'dev'
Requires-Dist: pytest-asyncio>=0.21.0; extra == 'dev'
Requires-Dist: pytest-cov>=4.0.0; extra == 'dev'
Requires-Dist: pytest>=7.0.0; extra == 'dev'
Requires-Dist: ruff>=0.1.0; extra == 'dev'
